{
    "data": [
        {
            "id": "1354351",
            "name": "Brodick Highland Games",
            "description": "Traditional village Highland games with athletics, a pipe band, heavy weights, Highland dancing and stalls.",
            "category": "Highland Games",
            "locationName": "North Ayrshire",
            "latitude": 55.57364,
            "longitude": -5.1584,
            "url": "/info/events/brodick-highland-games-p1354351",
            "image": "http://www.visitscotland.com/wsimgs/EF9CFBEFC8064438C331A3CF4A3FCE142FE7A6F6.jpg[ToFit600x400]",
            "minStars": 0,
            "maxStars": 0,
            "price": "0",
            "facilities": "",
            "distance": null,
            "basis": null,
            "website": "https://www.facebook.com/BrodickHighlandGames",
            "bookingUrl": null,
            "offers": 0,
            "externalReviewsID": null,
            "addressLine1": "Ormidale Park, Brodick.KA27 8BY",
            "multiplePrices": true,
            "startDate": "2020-08-08",
            "endDate": "2020-08-08",
            "telephoneNumber": null,
            "email": null,
            "tasteOurBestAward": false,
            "gold": false,
            "even": true
        }
    ]
}